pypeline/__init__.py
pypeline_tool-1.0.1.dist-info/LICENSE
pypeline_tool-1.0.1.dist-info/METADATA
pypeline_tool-1.0.1.dist-info/WHEEL
pypeline_tool-1.0.1.dist-info/top_level.txt
pypeline_tool-1.0.1.dist-info/RECORD
