Metadata-Version: 2.1
Name: pypeline-tool
Version: 1.0.1
Summary: Pipeline tool
Home-page: https://github.com/Pythonicos/pypeline
Author: Ohrlando
Author-email: pythonicos@outlook.com
License: MIT
Keywords: pipeline tasks chain
Platform: UNKNOWN
Classifier: Programming Language :: Python :: 3
Requires-Python: >=3
